py_dbcn/__init__.py
py_dbcn/constants.py
py_dbcn/logging.py
py_dbcn/connectors/__init__.py
py_dbcn/connectors/core/__init__.py
py_dbcn/connectors/core/clauses.py
py_dbcn/connectors/core/core.py
py_dbcn/connectors/core/database.py
py_dbcn/connectors/core/display.py
py_dbcn/connectors/core/query.py
py_dbcn/connectors/core/records.py
py_dbcn/connectors/core/tables.py
py_dbcn/connectors/core/utils.py
py_dbcn/connectors/core/validate.py
py_dbcn/connectors/mysql/__init__.py
py_dbcn/connectors/mysql/core.py
py_dbcn/connectors/mysql/database.py
py_dbcn/connectors/mysql/display.py
py_dbcn/connectors/mysql/query.py
py_dbcn/connectors/mysql/records.py
py_dbcn/connectors/mysql/tables.py
py_dbcn/connectors/mysql/utils.py
py_dbcn/connectors/mysql/validate.py
py_dbcn/connectors/postgresql/__init__.py
py_dbcn/connectors/postgresql/core.py
py_dbcn/connectors/postgresql/database.py
py_dbcn/connectors/postgresql/display.py
py_dbcn/connectors/postgresql/query.py
py_dbcn/connectors/postgresql/records.py
py_dbcn/connectors/postgresql/tables.py
py_dbcn/connectors/postgresql/utils.py
py_dbcn/connectors/postgresql/validate.py
py_dbcn/connectors/sqlite/__init__.py
py_dbcn/connectors/sqlite/core.py
py_dbcn/connectors/sqlite/database.py
py_dbcn/connectors/sqlite/display.py
py_dbcn/connectors/sqlite/query.py
py_dbcn/connectors/sqlite/records.py
py_dbcn/connectors/sqlite/tables.py
py_dbcn/connectors/sqlite/utils.py
py_dbcn/connectors/sqlite/validate.py
tests/__init__.py
tests/connectors/__init__.py
tests/connectors/core/__init__.py
tests/connectors/core/test_clauses.py
tests/connectors/core/test_core.py
tests/connectors/core/test_database.py
tests/connectors/core/test_display.py
tests/connectors/core/test_query.py
tests/connectors/core/test_records.py
tests/connectors/core/test_tables.py
tests/connectors/core/test_utils.py
tests/connectors/core/test_validate.py
tests/connectors/mysql/__init__.py
tests/connectors/mysql/constants.py
tests/connectors/mysql/expected_display_output.py
py_dbcn-0.4.0.dist-info/LICENSE
py_dbcn-0.4.0.dist-info/METADATA
py_dbcn-0.4.0.dist-info/WHEEL
py_dbcn-0.4.0.dist-info/top_level.txt
py_dbcn-0.4.0.dist-info/RECORD
