Metadata-Version: 2.1
Name: py-dbcn
Version: 0.4.0
Summary: Connector for Pythonic interaction with multiple database types.
Home-page: https://github.com/brodriguez8774/py-dbcn
Author: Brandon Rodriguez
Author-email: Brandon Rodriguez <brodriguez8774@gmail.com>
License: MIT License
Project-URL: Homepage, https://github.com/brodriguez8774/py-dbcn
Keywords: database,mysql,postgresql
Classifier: Intended Audience :: Developers
Classifier: License :: OSI Approved :: MIT License
Classifier: Operating System :: OS Independent
Classifier: Programming Language :: Python
Classifier: Programming Language :: Python :: 3
Classifier: Programming Language :: Python :: 3 :: Only
Classifier: Programming Language :: Python :: 3.7
Classifier: Programming Language :: Python :: 3.8
Classifier: Programming Language :: Python :: 3.9
Classifier: Programming Language :: Python :: 3.10
Requires-Python: >=3.7
License-File: LICENSE
Provides-Extra: dev
Requires-Dist: pip-tools ; extra == 'dev'
Provides-Extra: doc
Requires-Dist: pip-tools ; extra == 'doc'
Requires-Dist: sphinx ; extra == 'doc'
Requires-Dist: sphinx-autobuild ; extra == 'doc'
Requires-Dist: sphinx-rtd-theme ; extra == 'doc'
